coffeegrindsize/__init__.py
coffeegrindsize/scripts/__init__.py
coffeegrindsize/scripts/coffeegrindsize.py
coffeegrindsize-0.2.0.dist-info/LICENSE
coffeegrindsize-0.2.0.dist-info/METADATA
coffeegrindsize-0.2.0.dist-info/WHEEL
coffeegrindsize-0.2.0.dist-info/entry_points.txt
coffeegrindsize-0.2.0.dist-info/top_level.txt
coffeegrindsize-0.2.0.dist-info/RECORD
