Metadata-Version: 2.1
Name: coffeegrindsize
Version: 0.2.0
Summary: An app to measure your coffee grind size distribution
Home-page: https://github.com/austinkeller/coffeegrindsize
Author: Jonathan Gagné
Author-email: jonathan.gagne@montreal.ca
Maintainer: Austin Keller
Maintainer-email: atkeller@uw.edu
License: UNKNOWN
Platform: UNKNOWN
Classifier: Programming Language :: Python :: 3
Classifier: License :: OSI Approved :: MIT License
Classifier: Operating System :: OS Independent
Requires-Python: >=3.6
Requires-Dist: click
Requires-Dist: matplotlib
Requires-Dist: numpy
Requires-Dist: pandas
Requires-Dist: Pillow
